feat_extractor/__init__.py
feat_extractor/feat_extractor.py
feat_extractor-0.0.6.dist-info/METADATA
feat_extractor-0.0.6.dist-info/WHEEL
feat_extractor-0.0.6.dist-info/top_level.txt
feat_extractor-0.0.6.dist-info/RECORD
