Metadata-Version: 2.1
Name: feat-extractor
Version: 0.0.6
Summary: Gtzan feature Extractor
Author: ranierifr
License: MIT
Requires-Python: >=3.6
